mcp_trace/__init__.py
mcp_trace/middleware.py
mcp_trace/adapters/__init__.py
mcp_trace/adapters/base.py
mcp_trace/adapters/console_adapter.py
mcp_trace/adapters/contexaai_adapter.py
mcp_trace/adapters/file_adapter.py
mcp_trace/adapters/postgres_adapter.py
mcp_trace/adapters/supabase_adapter.py
mcp_trace-0.1.7.dist-info/METADATA
mcp_trace-0.1.7.dist-info/WHEEL
mcp_trace-0.1.7.dist-info/top_level.txt
mcp_trace-0.1.7.dist-info/RECORD
