Metadata-Version: 2.4
Name: mcp-trace
Version: 0.1.7
Summary: Open-source tracing middleware for MCP servers. Export logs, requests, and tool calls to files, PostgreSQL, Supabase, Contexa, or custom backends with full control over what gets logged.
Author-email: Akshay Galande <mybytecode@gmail.com>
Maintainer-email: Akshay Galande <mybytecode@gmail.com>
Project-URL: Homepage, https://github.com/contexaAI/mcp-trace
Project-URL: Documentation, https://github.com/contexaAI/mcp-trace#readme
Project-URL: Repository, https://github.com/contexaAI/mcp-trace.git
Project-URL: Issues, https://github.com/contexaAI/mcp-trace/issues
Project-URL: Changelog, https://github.com/contexaAI/mcp-trace/releases
Project-URL: Bug Tracker, https://github.com/contexaAI/mcp-trace/issues
Project-URL: Source Code, https://github.com/contexaAI/mcp-trace
Project-URL: Discussions, https://github.com/contexaAI/mcp-trace/discussions
Project-URL: Funding, https://github.com/sponsors/contexaAI
Project-URL: Twitter, https://twitter.com/contexaAI
Keywords: mcp,model-context-protocol,tracing,logging,fastmcp,middleware,observability,monitoring,postgresql,supabase,contexa
Classifier: Development Status :: 4 - Beta
Classifier: Intended Audience :: Developers
Classifier: License :: OSI Approved :: MIT License
Classifier: Operating System :: OS Independent
Classifier: Programming Language :: Python
Classifier: Programming Language :: Python :: 3
Classifier: Programming Language :: Python :: 3.8
Classifier: Programming Language :: Python :: 3.9
Classifier: Programming Language :: Python :: 3.10
Classifier: Programming Language :: Python :: 3.11
Classifier: Programming Language :: Python :: 3.12
Classifier: Topic :: Software Development
Classifier: Topic :: Software Development :: Libraries
Classifier: Topic :: Software Development :: Libraries :: Python Modules
Classifier: Topic :: System :: Logging
Classifier: Topic :: System :: Monitoring
Requires-Python: >=3.8
Requires-Dist: psycopg2-binary
Requires-Dist: requests
Requires-Dist: pydantic
Requires-Dist: supabase
Requires-Dist: mcp[cli]
Provides-Extra: dev
Requires-Dist: pytest>=7.0.0; extra == "dev"
Requires-Dist: pytest-cov>=4.0.0; extra == "dev"
Requires-Dist: black>=23.0.0; extra == "dev"
Requires-Dist: ruff>=0.1.0; extra == "dev"
Requires-Dist: mypy>=1.0.0; extra == "dev"
Provides-Extra: postgres
Requires-Dist: psycopg2-binary>=2.9.0; extra == "postgres"
Provides-Extra: all
Requires-Dist: psycopg2-binary>=2.9.0; extra == "all"
